guardpycfn-0.1.0.dist-info/METADATA
guardpycfn-0.1.0.dist-info/WHEEL
guardpycfn-0.1.0.dist-info/licenses/LICENSE
guardpycfn/__init__.py
guardpycfn/guardpycfn.abi3.so
guardpycfn-0.1.0.dist-info/RECORD
